img2feat/__init__.py
img2feat/antbee.py
img2feat/aug.py
img2feat/buildnet.py
img2feat/cnn.py
tests/__init__.py
tests/test_img2feat.py
img2feat-0.3.0.dist-info/METADATA
img2feat-0.3.0.dist-info/WHEEL
img2feat-0.3.0.dist-info/top_level.txt
img2feat-0.3.0.dist-info/RECORD
