Metadata-Version: 2.1
Name: img2feat
Version: 0.3.0
Summary: Convert image to feature based on convolutional neural network (CNN).
Home-page: https://github.com/mastnk/img2feat
Author: Masayuki Tanaka
Author-email: mastnk@gmail.com
Classifier: License :: OSI Approved :: GNU Library or Lesser General Public License (LGPL)
Classifier: Programming Language :: Python :: 3.6
Requires-Dist: scikit-learn
Requires-Dist: numpy
Requires-Dist: torch
Requires-Dist: torchvision
Requires-Dist: opencv-python
Requires-Dist: scikit-build
Requires-Dist: cmake
Requires-Dist: scipy
